rqdatac/__init__.py
rqdatac/__init__.pyi
rqdatac/_internal.py
rqdatac/_version.py
rqdatac/client.py
rqdatac/connection.cpp
rqdatac/connection.cpython-36m-x86_64-linux-gnu.so
rqdatac/connection_pool.py
rqdatac/decorators.py
rqdatac/hk_decorators.py
rqdatac/rqdatah_helper.py
rqdatac/thread_local.py
rqdatac/utils.py
rqdatac/validators.py
rqdatac/services/__init__.py
rqdatac/services/async_live_md_client.py
rqdatac/services/basic.py
rqdatac/services/calendar.py
rqdatac/services/concept.py
rqdatac/services/consensus.py
rqdatac/services/constant.py
rqdatac/services/convertible.py
rqdatac/services/extra.py
rqdatac/services/factor.py
rqdatac/services/financial.py
rqdatac/services/future.py
rqdatac/services/get_capital_flow.py
rqdatac/services/get_price.py
rqdatac/services/index.py
rqdatac/services/ksh_auction_info.py
rqdatac/services/live.py
rqdatac/services/live_md_client.py
rqdatac/services/market_data.py
rqdatac/services/options.py
rqdatac/services/shenwan.py
rqdatac/services/stock_status.py
rqdatac/services/structured_fund.py
rqdatac/services/tmall.py
rqdatac/services/xueqiu.py
rqdatac/services/detail/__init__.py
rqdatac/services/detail/adjust_price.py
rqdatac/services/detail/get_price_df.py
rqdatac/services/detail/resample_helper.py
rqdatac/services/orm/__init__.py
rqdatac/services/orm/hk_pit_financials_ex.py
rqdatac/services/orm/pit_financials_ex.py
rqdatac/share/__init__.py
rqdatac/share/codec.py
rqdatac/share/errors.py
rqdatac/share/protocol.py
rqdatac-3.4.2.dist-info/METADATA
rqdatac-3.4.2.dist-info/WHEEL
rqdatac-3.4.2.dist-info/top_level.txt
rqdatac-3.4.2.dist-info/RECORD
